torch_cka/__init__.py
torch_cka/cka.py
torch_cka/utils.py
torch_cka-0.21.dist-info/LICENSE.md
torch_cka-0.21.dist-info/METADATA
torch_cka-0.21.dist-info/WHEEL
torch_cka-0.21.dist-info/top_level.txt
torch_cka-0.21.dist-info/RECORD
