Metadata-Version: 2.1
Name: torch-cka
Version: 0.21
Summary: A package to compare neural networks by their feature similarity
Home-page: https://github.com/AntixK/PyTorch-Model-Compare
Author: Anand K Subramanian
Author-email: anandkrish894@gmail.com
License: UNKNOWN
Project-URL: Bug Tracker, https://github.com/AntixK/PyTorch-Model-Compare/issues
Platform: UNKNOWN
Classifier: Programming Language :: Python :: 3
Classifier: License :: OSI Approved :: MIT License
Classifier: Operating System :: OS Independent
Requires-Python: >=3.7
License-File: LICENSE.md
